value_object_pattern/__init__.py
value_object_pattern/py.typed
value_object_pattern/models/__init__.py
value_object_pattern/models/value_object.py
value_object_pattern-2025.1.3.dist-info/METADATA
value_object_pattern-2025.1.3.dist-info/WHEEL
value_object_pattern-2025.1.3.dist-info/licenses/LICENSE.md
value_object_pattern-2025.1.3.dist-info/RECORD
