Metadata-Version: 2.4
Name: value-object-pattern
Version: 2025.1.3
Summary: The Value Object Pattern is a Python package that streamlines the creation and management of value objects in your projects.
Project-URL: Homepage, https://github.com/adriamontoto/value-object-pattern
Project-URL: Repository, https://github.com/adriamontoto/value-object-pattern
Project-URL: Issues, https://github.com/adriamontoto/value-object-pattern/issues
Author: Adria Montoto
License-Expression: MIT
License-File: LICENSE.md
Keywords: development,domain-driven-design,encapsulation,pattern,python,tools,utilities,validation,value-object
Classifier: Intended Audience :: Developers
Classifier: License :: OSI Approved :: MIT License
Classifier: Operating System :: OS Independent
Classifier: Programming Language :: Python
Classifier: Programming Language :: Python :: 3
Classifier: Programming Language :: Python :: 3.11
Classifier: Programming Language :: Python :: 3.12
Classifier: Programming Language :: Python :: 3.13
Classifier: Typing :: Typed
Requires-Python: >=3.11
Provides-Extra: tests
Requires-Dist: coverage[toml]<8.0.0,>=7.0.0; extra == 'tests'
Requires-Dist: mypy[reports]<2.0.0,>=1.0.0; extra == 'tests'
Requires-Dist: object-mother-pattern>=2025.01.03; extra == 'tests'
Requires-Dist: pre-commit<5.0.0,>=3.0.0; extra == 'tests'
Requires-Dist: pytest-randomly<4.0.0,>=3.0.0; extra == 'tests'
Requires-Dist: pytest<9.0.0,>=8.0.0; extra == 'tests'
Requires-Dist: ruff<1.0.0,>=0.0.0; extra == 'tests'
